mlp_tracking/__init__.py
mlp_tracking/constants.py
mlp_tracking/kafka_helper.py
mlp_tracking/log_helper.py
mlp_tracking/mlp_tracker.py
mlp_tracking/util.py
mlp_tracking-0.0.3.dist-info/METADATA
mlp_tracking-0.0.3.dist-info/WHEEL
mlp_tracking-0.0.3.dist-info/top_level.txt
mlp_tracking-0.0.3.dist-info/RECORD
