Metadata-Version: 2.1
Name: mlp-tracking
Version: 0.0.3
Summary: mlp_tracking
Home-page: UNKNOWN
Author: hazoth, LowinLi
Author-email: hazoth@hotmail.com, idealway9@gmail.com
License: UNKNOWN
Keywords: kafka issue tracking
Platform: UNKNOWN
Classifier: Programming Language :: Python :: 3
Classifier: License :: OSI Approved :: MIT License
Classifier: Operating System :: OS Independent
Requires-Dist: confluent-kafka (==1.7.0)
Requires-Dist: ml-platform-client (>=0.3.18.5)
